odoo/addons/shopinvader_mass_mailing_company_newsletter/README.rst
odoo/addons/shopinvader_mass_mailing_company_newsletter/__init__.py
odoo/addons/shopinvader_mass_mailing_company_newsletter/__manifest__.py
odoo/addons/shopinvader_mass_mailing_company_newsletter/i18n/shopinvader_mass_mailing_company_newsletter.pot
odoo/addons/shopinvader_mass_mailing_company_newsletter/readme/CONTRIBUTORS.rst
odoo/addons/shopinvader_mass_mailing_company_newsletter/readme/DESCRIPTION.rst
odoo/addons/shopinvader_mass_mailing_company_newsletter/services/__init__.py
odoo/addons/shopinvader_mass_mailing_company_newsletter/services/address.py
odoo/addons/shopinvader_mass_mailing_company_newsletter/static/description/index.html
odoo/addons/shopinvader_mass_mailing_company_newsletter/tests/__init__.py
odoo/addons/shopinvader_mass_mailing_company_newsletter/tests/test_mass_mailing_company_newsletter.py
odoo14_addon_shopinvader_mass_mailing_company_newsletter-14.0.1.0.1.dist-info/METADATA
odoo14_addon_shopinvader_mass_mailing_company_newsletter-14.0.1.0.1.dist-info/WHEEL
odoo14_addon_shopinvader_mass_mailing_company_newsletter-14.0.1.0.1.dist-info/top_level.txt
odoo14_addon_shopinvader_mass_mailing_company_newsletter-14.0.1.0.1.dist-info/RECORD
